OffSecIta/__init__.py
OffSecIta/corsi.py
OffSecIta/utils.py
OffSecIta1-0.1.2.dist-info/METADATA
OffSecIta1-0.1.2.dist-info/WHEEL
OffSecIta1-0.1.2.dist-info/top_level.txt
OffSecIta1-0.1.2.dist-info/RECORD
