Metadata-Version: 2.1
Name: OffSecIta1
Version: 0.1.2
Summary: Biblioteca per consultare i corsi
Home-page: https://www.youtube.com/@Roby_kali
Author: Mr.Manimal
